pass_by_value/__init__.py
pass_by_value/decorator.py
pass_by_value-0.1.0.dist-info/LICENSE
pass_by_value-0.1.0.dist-info/WHEEL
pass_by_value-0.1.0.dist-info/METADATA
pass_by_value-0.1.0.dist-info/RECORD
