Metadata-Version: 2.1
Name: pass-by-value
Version: 0.1.0
Summary: Passing by value in Python functions
Home-page: https://github.com/petereon/pass_by_val
License: MIT
Keywords: python
Author: Peter Vyboch
Author-email: pvyboch1@gmail.com
Requires-Python: >=3.9,<4.0
Classifier: License :: OSI Approved :: MIT License
Classifier: Programming Language :: Python :: 3
Classifier: Programming Language :: Python :: 3.10
Classifier: Programming Language :: Python :: 3.9
Project-URL: Repository, https://github.com/petereon/pass_by_val
